imageprep/__init__.py
imageprep/coco.py
imageprep/imcli.py
imageprep/utils.py
imageprep/voc.py
imageprep/yolo.py
tests/__init__.py
tests/test_coco.py
tests/test_utils.py
tests/test_voc.py
tests/test_yolo.py
tests/data/__init__.py
tests/data/labels/__init__.py
imageprep-0.3.dist-info/LICENSE.txt
imageprep-0.3.dist-info/METADATA
imageprep-0.3.dist-info/WHEEL
imageprep-0.3.dist-info/entry_points.txt
imageprep-0.3.dist-info/top_level.txt
imageprep-0.3.dist-info/RECORD
